{
  "parent": "minecraft:recipes/root",
  "criteria": {
    "has_gold_paxel": {
      "conditions": {
        "items": [
          {
            "items": [
              "mekanismtools:gold_paxel"
            ]
          }
        ]
      },
      "trigger": "minecraft:inventory_changed"
    },
    "has_the_recipe": {
      "conditions": {
        "recipe": "minecraft:gold_nugget_from_blasting_gold_paxel"
      },
      "trigger": "minecraft:recipe_unlocked"
    }
  },
  "requirements": [
    [
      "has_gold_paxel",
      "has_the_recipe"
    ]
  ],
  "rewards": {
    "recipes": [
      "minecraft:gold_nugget_from_blasting_gold_paxel"
    ]
  },
  "sends_telemetry_event": false
}